nonebot_plugin_quark_autosave/__init__.py
nonebot_plugin_quark_autosave/client.py
nonebot_plugin_quark_autosave/config.py
nonebot_plugin_quark_autosave/exception.py
nonebot_plugin_quark_autosave/model.py
nonebot_plugin_quark_autosave-0.1.9.dist-info/WHEEL
nonebot_plugin_quark_autosave-0.1.9.dist-info/METADATA
nonebot_plugin_quark_autosave-0.1.9.dist-info/RECORD
