Metadata-Version: 2.3
Name: nonebot-plugin-quark-autosave
Version: 0.1.9
Summary: 配合 quark-auto-save(https://github.com/Cp0204/quark-auto-save) 使用, 支持添加，删除，列出，运行任务
Author: fllesser
Author-email: fllesser <fllessive@gmail.com>
Requires-Dist: httpx>=0.27.0,<1.0.0
Requires-Dist: nonebot-plugin-alconna>=0.59.4,<1.0.0
Requires-Dist: nonebot2>=2.4.3,<3.0.0
Requires-Python: >=3.10
Project-URL: Repository, https://github.com/fllesser/nonebot-plugin-quark-autosave
